{
  "total_pages": 3,
  "stats": {
    "header": 7,
    "title": 12,
    "text": 34,
    "footer": 3,
    "table_title": 1,
    "table": 1,
    "stamp": 4
  },
  "contents": [
    {
      "page": 1,
      "position": [
        835,
        112,
        961,
        112,
        961,
        132,
        835,
        132
      ],
      "type": "header",
      "content": "图书采购合同"
    },
    {
      "page": 1,
      "position": [
        230,
        114,
        357,
        114,
        357,
        134,
        230,
        134
      ],
      "type": "header",
      "content": "宁夏医科大学"
    },
    {
      "page": 1,
      "position": [
        210,
        204,
        970,
        200,
        969,
        244,
        209,
        248
      ],
      "type": "title",
      "level": 0,
      "content": "宁夏医科大学文献资源招标（采购）合同"
    },
    {
      "page": 1,
      "position": [
        306,
        388,
        878,
        386,
        877,
        416,
        305,
        418
      ],
      "type": "title",
      "level": 1,
      "content": "项目名称：宁夏医科大学2019年图书馆文献"
    },
    {
      "page": 1,
      "position": [
        454,
        449,
        832,
        449,
        832,
        478,
        454,
        478
      ],
      "type": "title",
      "level": 1,
      "content": "资源（中文纸本文献）建设项目"
    },
    {
      "page": 1,
      "position": [
        314,
        627,
        869,
        625,
        869,
        655,
        313,
        657
      ],
      "type": "text",
      "content": "招标代理机构：中天世纪国际招标有限公司"
    },
    {
      "page": 1,
      "position": [
        385,
        894,
        736,
        894,
        736,
        923,
        385,
        923
      ],
      "type": "text",
      "content": "委托编号：2019NCZ001726W"
    },
    {
      "page": 1,
      "position": [
        384,
        981,
        749,
        978,
        749,
        1007,
        384,
        1010
      ],
      "type": "text",
      "content": "招标编号：ZTSJ-NZC/A19251"
    },
    {
      "page": 1,
      "position": [
        510,
        1187,
        689,
        1187,
        689,
        1215,
        510,
        1215
      ],
      "type": "text",
      "content": "2019年10月"
    },
    {
      "page": 1,
      "position": [
        449,
        1246,
        741,
        1246,
        741,
        1277,
        449,
        1277
      ],
      "type": "text",
      "content": "宁夏医科大学图书馆制"
    },
    {
      "page": 1,
      "position": [
        587,
        1525,
        605,
        1525,
        605,
        1548,
        587,
        1548
      ],
      "type": "footer",
      "content": "1"
    },
    {
      "page": 2,
      "position": [
        833,
        111,
        958,
        111,
        958,
        132,
        833,
        132
      ],
      "type": "header",
      "content": "图书采购合同"
    },
    {
      "page": 2,
      "position": [
        235,
        116,
        358,
        114,
        358,
        135,
        234,
        137
      ],
      "type": "header",
      "content": "宁夏医科大学"
    },
    {
      "page": 2,
      "position": [
        189,
        158,
        560,
        155,
        560,
        184,
        188,
        187
      ],
      "type": "text",
      "content": "**甲方（采购方）：宁夏医科大学**"
    },
    {
      "page": 2,
      "position": [
        189,
        210,
        721,
        208,
        721,
        236,
        188,
        239
      ],
      "type": "text",
      "content": "**乙方（供货方）：湖北三新文化传媒有限公司**"
    },
    {
      "page": 2,
      "position": [
        189,
        265,
        483,
        262,
        482,
        291,
        188,
        294
      ],
      "type": "text",
      "content": "**签定地点：宁夏医科大学**"
    },
    {
      "page": 2,
      "position": [
        188,
        304,
        1001,
        304,
        1001,
        425,
        188,
        425
      ],
      "type": "text",
      "content": "依照《中华人民共和国合同法》、《中华人民共和国政府采购法》及宁夏回族自治区和宁夏医科大学的相关规定，严格按照招标文件及乙方的投标文件，甲乙双方签定如下合同："
    },
    {
      "page": 2,
      "position": [
        238,
        441,
        618,
        438,
        617,
        467,
        237,
        469
      ],
      "type": "title",
      "level": 1,
      "content": "第一条 本合同图书折扣及金额"
    },
    {
      "page": 2,
      "position": [
        237,
        485,
        417,
        485,
        417,
        512,
        237,
        512
      ],
      "type": "title",
      "level": 2,
      "content": "1．本合同金额"
    },
    {
      "page": 2,
      "position": [
        227,
        529,
        631,
        525,
        630,
        554,
        226,
        557
      ],
      "type": "text",
      "content": "**本合同金额：（大写）伍拾万元整**"
    },
    {
      "page": 2,
      "position": [
        396,
        573,
        666,
        573,
        666,
        600,
        396,
        600
      ],
      "type": "text",
      "content": "**（小写）¥500000.00元**"
    },
    {
      "page": 2,
      "position": [
        240,
        618,
        470,
        615,
        469,
        644,
        239,
        647
      ],
      "type": "table_title",
      "content": "**2．本合同图书折扣**"
    },
    {
      "type": "table",
      "page": 2,
      "position": [
        225,
        652,
        988,
        647,
        988,
        772,
        226,
        776
      ],
      "structured": {
        "headers": [
          {
            "text": "序号"
          },
          {
            "text": "名称"
          },
          {
            "text": "型号和规格"
          },
          {
            "text": "数量"
          },
          {
            "text": "折扣"
          }
        ],
        "rows": [
          [
            {
              "text": "1"
            },
            {
              "text": "中文纸本图书",
              "row_span": 2
            },
            {
              "text": "生物卫生医药类"
            },
            {
              "text": "1 批",
              "row_span": 2
            },
            {
              "text": "小写：70 % 大写：百分之柒拾"
            }
          ],
          [
            {
              "text": "2"
            },
            {
              "text": "其他类图书"
            },
            {
              "text": "小写：70％大写：百分之柒拾"
            }
          ]
        ]
      },
      "html": "<table border=\"1\" ><tr>\n<td>序号</td>\n<td>名称</td>\n<td>型号和规格</td>\n<td>数量</td>\n<td>折扣</td>\n</tr><tr>\n<td>1</td>\n<td rowspan=\"2\">中文纸本图书</td>\n<td>生物卫生医药类</td>\n<td rowspan=\"2\">1 批</td>\n<td>小写：70 % 大写：百分之柒拾</td>\n</tr><tr>\n<td>2</td>\n<td>其他类图书</td>\n<td>小写：70％大写：百分之柒拾</td>\n</tr></table>",
      "caption_page": 2,
      "caption_index": 11
    },
    {
      "page": 2,
      "position": [
        245,
        785,
        459,
        785,
        459,
        812,
        245,
        812
      ],
      "type": "title",
      "level": 1,
      "content": "第二条 质量要求"
    },
    {
      "page": 2,
      "position": [
        193,
        819,
        1001,
        819,
        1001,
        893,
        193,
        893
      ],
      "type": "text",
      "content": "1．乙方提供的图书必须符合甲方招标文件要求及乙方投标文件中规定的质量要求和验收标准。"
    },
    {
      "page": 2,
      "position": [
        190,
        899,
        1004,
        899,
        1004,
        1055,
        190,
        1055
      ],
      "type": "text",
      "content": "2．乙方必须保证所提供图书符合《出版管理条例》、国家版权法及其它法律之规定，必须是正式出版社出版的正规、正版图书，不得夹杂非法、盗版、盗印出版物，不得将特价图书视做新书混合供应。如有违反，乙方应承担由此带来的全部责任，并立即终止合同。"
    },
    {
      "page": 2,
      "position": [
        228,
        1067,
        689,
        1063,
        688,
        1092,
        228,
        1096
      ],
      "type": "title",
      "level": 1,
      "content": "第三条 交（提）货时间、地点、要求"
    },
    {
      "page": 2,
      "position": [
        191,
        1099,
        1007,
        1099,
        1007,
        1176,
        191,
        1176
      ],
      "type": "text",
      "content": "1．交货期限：在合同终止前，乙方分批次将甲方所采购图书送达甲方，并按甲方要求完成图书加工任务。"
    },
    {
      "page": 2,
      "position": [
        240,
        1188,
        661,
        1184,
        660,
        1213,
        239,
        1217
      ],
      "type": "text",
      "content": "2．交货地点：宁夏医科大学图书馆"
    },
    {
      "page": 2,
      "position": [
        241,
        1226,
        726,
        1223,
        726,
        1257,
        241,
        1260
      ],
      "type": "text",
      "content": "3．运输、保险及装卸费用均由乙方承担。"
    },
    {
      "page": 2,
      "position": [
        241,
        1269,
        968,
        1263,
        967,
        1291,
        241,
        1297
      ],
      "type": "text",
      "content": "4．乙方所供货物应按有关标准进行包装，做好必要保护措施。"
    },
    {
      "page": 2,
      "position": [
        241,
        1309,
        623,
        1306,
        622,
        1335,
        241,
        1338
      ],
      "type": "title",
      "level": 1,
      "content": "第四条 验收时间、标准及方法"
    },
    {
      "page": 2,
      "position": [
        194,
        1343,
        1007,
        1343,
        1007,
        1418,
        194,
        1418
      ],
      "type": "text",
      "content": "1．乙方应按照标书所作承诺，根据甲方的技术规范要求，完成图书加工后方可验收。"
    },
    {
      "page": 2,
      "position": [
        191,
        1423,
        1007,
        1423,
        1007,
        1500,
        191,
        1500
      ],
      "type": "text",
      "content": "2．甲方在图书验收过程中，若发现有错发、缺损、缺页、装订、印刷、随书附件等质量问题，乙方必须免费更换或退货，并承担产生"
    },
    {
      "page": 2,
      "position": [
        590,
        1529,
        608,
        1529,
        608,
        1548,
        590,
        1548
      ],
      "type": "footer",
      "content": "2"
    },
    {
      "page": 3,
      "position": [
        832,
        112,
        958,
        112,
        958,
        132,
        832,
        132
      ],
      "type": "header",
      "content": "图书采购合同"
    },
    {
      "page": 3,
      "position": [
        228,
        116,
        355,
        116,
        355,
        136,
        228,
        136
      ],
      "type": "header",
      "content": "宁夏医科大学"
    },
    {
      "page": 3,
      "position": [
        179,
        148,
        327,
        148,
        327,
        174,
        179,
        174
      ],
      "type": "header",
      "content": "的所有费用。"
    },
    {
      "page": 3,
      "position": [
        232,
        187,
        587,
        184,
        586,
        213,
        231,
        215
      ],
      "type": "title",
      "level": 1,
      "content": "第五条 货款结算与支付方式"
    },
    {
      "page": 3,
      "position": [
        178,
        221,
        999,
        221,
        999,
        374,
        178,
        374
      ],
      "type": "text",
      "content": "合同签订后，乙方在合同期内分批次向甲方供应图书，甲方验收合格后按合同款额的90％支付货款，验收之日六个月后，乙方全部执行合同相应条款且提供服务履行合同无任何质量问题，甲方向乙方支付合同款额的10％。"
    },
    {
      "page": 3,
      "position": [
        232,
        387,
        454,
        385,
        453,
        413,
        231,
        415
      ],
      "type": "title",
      "level": 1,
      "content": "第六条 违约责任"
    },
    {
      "page": 3,
      "position": [
        180,
        422,
        1001,
        422,
        1001,
        535,
        180,
        535
      ],
      "type": "text",
      "content": "1．甲乙双方必须严格执行本合同，若任何一方要求变更供货要求、验收、结算日期，应首先取得甲乙双方书面协议共同确认，并承担由此给对方造成的直接损失。"
    },
    {
      "page": 3,
      "position": [
        181,
        542,
        1001,
        542,
        1001,
        615,
        181,
        615
      ],
      "type": "text",
      "content": "2．任何一方无正当理由取消合同，则应向对方支付本合同总金额的10％作为违约赔偿金。"
    },
    {
      "page": 3,
      "position": [
        181,
        621,
        1002,
        621,
        1002,
        696,
        181,
        696
      ],
      "type": "text",
      "content": "3．乙方如不能按期供货或履行合同，甲方可从货款中逐日扣取5‰作为违约赔偿金。"
    },
    {
      "page": 3,
      "position": [
        182,
        703,
        1003,
        703,
        1003,
        776,
        182,
        776
      ],
      "type": "text",
      "content": "4．合同执行过程中出现的其它违约情况均按《中华人民共和国合同法》执行。"
    },
    {
      "page": 3,
      "position": [
        182,
        783,
        1003,
        783,
        1003,
        860,
        182,
        860
      ],
      "type": "title",
      "level": 1,
      "content": "第七条 合同正本一式陆份，甲方持叁份（图书馆、校办、财务处），乙方持叁份。"
    },
    {
      "page": 3,
      "position": [
        182,
        862,
        1003,
        862,
        1003,
        942,
        182,
        942
      ],
      "type": "title",
      "level": 1,
      "content": "第八条 合同出现争议，双方协商解决，协商达不成一致由甲方所在地人民法院裁决。"
    },
    {
      "type": "stamp",
      "page": 3,
      "position": [
        291,
        848,
        533,
        847,
        534,
        1082,
        292,
        1083
      ],
      "stamp": {
        "type": "公章",
        "shape": "圆章",
        "color": "红色",
        "content": "宁夏医科大学    合同专用章"
      },
      "text": "宁夏医科大学    合同专用章"
    },
    {
      "type": "stamp",
      "page": 3,
      "position": [
        840,
        871,
        1078,
        869,
        1079,
        1103,
        841,
        1105
      ],
      "stamp": {
        "type": "公章",
        "shape": "圆章",
        "color": "红色",
        "content": "湖北三新文化传媒有限公司    合同专用章    4201070160123"
      },
      "text": "湖北三新文化传媒有限公司    合同专用章    4201070160123"
    },
    {
      "page": 3,
      "position": [
        603,
        1021,
        1002,
        1017,
        1003,
        1052,
        603,
        1056
      ],
      "type": "text",
      "content": "乙方：湖北三新文化传媒有限公司"
    },
    {
      "page": 3,
      "position": [
        222,
        1023,
        457,
        1021,
        457,
        1056,
        222,
        1059
      ],
      "type": "text",
      "content": "甲方：宁夏医科大学"
    },
    {
      "type": "stamp",
      "page": 3,
      "position": [
        421,
        1095,
        541,
        1095,
        540,
        1213,
        420,
        1212
      ],
      "stamp": {
        "type": "个人章",
        "shape": "方章",
        "color": "红色",
        "content": "孙涛之印"
      },
      "text": "孙涛之印"
    },
    {
      "type": "stamp",
      "page": 3,
      "position": [
        732,
        1066,
        848,
        1065,
        850,
        1181,
        733,
        1182
      ],
      "stamp": {
        "type": "专用章",
        "shape": "方章",
        "color": "红色",
        "content": "宋相濡印"
      },
      "text": "宋相濡印"
    },
    {
      "page": 3,
      "position": [
        608,
        1138,
        730,
        1138,
        730,
        1165,
        608,
        1165
      ],
      "type": "text",
      "content": "法人代表："
    },
    {
      "page": 3,
      "position": [
        220,
        1141,
        342,
        1141,
        342,
        1168,
        220,
        1168
      ],
      "type": "text",
      "content": "法人代表："
    },
    {
      "page": 3,
      "position": [
        608,
        1215,
        705,
        1215,
        705,
        1242,
        608,
        1242
      ],
      "type": "text",
      "content": "代理人："
    },
    {
      "page": 3,
      "position": [
        222,
        1206,
        524,
        1206,
        524,
        1267,
        222,
        1267
      ],
      "type": "text",
      "content": "主管校领导： 刘志君"
    },
    {
      "page": 3,
      "position": [
        220,
        1266,
        516,
        1266,
        516,
        1339,
        220,
        1339
      ],
      "type": "text",
      "content": "部门负责人： 王雪珍"
    },
    {
      "page": 3,
      "position": [
        610,
        1268,
        884,
        1271,
        882,
        1345,
        610,
        1341
      ],
      "type": "text",
      "content": "经办人： 在凯莉"
    },
    {
      "page": 3,
      "position": [
        610,
        1353,
        917,
        1350,
        918,
        1412,
        610,
        1415
      ],
      "type": "text",
      "content": "签字日期： 2019.11.1"
    },
    {
      "page": 3,
      "position": [
        221,
        1356,
        537,
        1356,
        537,
        1415,
        221,
        1415
      ],
      "type": "text",
      "content": "签字日期： 2019.11.1"
    },
    {
      "page": 3,
      "position": [
        585,
        1527,
        605,
        1527,
        605,
        1550,
        585,
        1550
      ],
      "type": "footer",
      "content": "3"
    }
  ]
}