{
  "file": "cc98476b82e57551a8e402f9a421072b_textin.json",
  "total_pages": 3,
  "stats": {
    "title": 11,
    "text": 47,
    "table_title": 1,
    "table": 1,
    "stamp": 2
  },
  "contents": [
    {
      "page": 1,
      "position": [
        1320,
        356,
        2466,
        356,
        2466,
        469,
        1320,
        469
      ],
      "type": "title",
      "level": 0,
      "content": "宁夏大学政府采购合同"
    },
    {
      "page": 1,
      "position": [
        370,
        703,
        1438,
        703,
        1438,
        789,
        370,
        789
      ],
      "type": "text",
      "content": "委托编号： 2019NCZ001618W"
    },
    {
      "page": 1,
      "position": [
        1988,
        706,
        3097,
        706,
        3097,
        793,
        1988,
        793
      ],
      "type": "text",
      "content": "竞价编号：20190627JJ0006W"
    },
    {
      "page": 1,
      "position": [
        370,
        863,
        1654,
        863,
        1654,
        961,
        370,
        961
      ],
      "type": "text",
      "content": "买 方：宁夏大学（研究生院）"
    },
    {
      "page": 1,
      "position": [
        1901,
        863,
        2835,
        863,
        2835,
        966,
        1901,
        966
      ],
      "type": "text",
      "content": "电 话：09512061502"
    },
    {
      "page": 1,
      "position": [
        370,
        1027,
        1654,
        1027,
        1654,
        1118,
        370,
        1118
      ],
      "type": "text",
      "content": "卖方：银川泽睿商贸有限公司"
    },
    {
      "page": 1,
      "position": [
        1988,
        1022,
        3010,
        1022,
        3010,
        1130,
        1988,
        1130
      ],
      "type": "text",
      "content": "电 话： 0951-5197939"
    },
    {
      "page": 1,
      "position": [
        370,
        1186,
        3416,
        1186,
        3416,
        1599,
        370,
        1599
      ],
      "type": "text",
      "content": "根据《中华人民共和国政府采购法》《中华人民共和国合同法》和有关政府采购法规，依据公开招标文件及投标书，经买卖双方商定，同意按如下条款和条件签订本合同："
    },
    {
      "page": 1,
      "position": [
        627,
        1674,
        2435,
        1674,
        2435,
        1764,
        627,
        1764
      ],
      "type": "table_title",
      "content": "（一）卖方应严格按照如下清单的要求提交货物"
    },
    {
      "type": "table",
      "page": 1,
      "position": [
        398,
        1792,
        3398,
        1802,
        3394,
        2575,
        394,
        2565
      ],
      "structured": {
        "headers": [
          {
            "text": "货物名称"
          },
          {
            "text": "型号规格"
          },
          {
            "text": "数量"
          },
          {
            "text": "单价"
          },
          {
            "text": "总价"
          }
        ],
        "rows": [
          [
            {
              "text": "其他文印设备"
            },
            {
              "text": "金图ST-10"
            },
            {
              "text": "1"
            },
            {
              "text": "32900.00"
            },
            {
              "text": "32900.00"
            }
          ],
          [
            {
              "text": "其他打印设备"
            },
            {
              "text": "斑马GT-800"
            },
            {
              "text": "2"
            },
            {
              "text": "2000.00"
            },
            {
              "text": "4000.00"
            }
          ],
          [
            {
              "text": "合计（大写）：叁万陆仟玖佰元整",
              "col_span": 4
            },
            {
              "text": "36900.00"
            }
          ]
        ]
      },
      "html": "<table border=\"1\" ><tr>\n<td>货物名称</td>\n<td>型号规格</td>\n<td>数量</td>\n<td>单价</td>\n<td>总价</td>\n</tr><tr>\n<td>其他文印设备</td>\n<td>金图ST-10</td>\n<td>1</td>\n<td>32900.00</td>\n<td>32900.00</td>\n</tr><tr>\n<td>其他打印设备</td>\n<td>斑马GT-800</td>\n<td>2</td>\n<td>2000.00</td>\n<td>4000.00</td>\n</tr><tr>\n<td colspan=\"4\">合计（大写）：叁万陆仟玖佰元整</td>\n<td>36900.00</td>\n</tr></table>",
      "caption_page": 1,
      "caption_index": 11
    },
    {
      "page": 1,
      "position": [
        550,
        2624,
        2763,
        2624,
        2763,
        2723,
        550,
        2723
      ],
      "type": "text",
      "content": "**合同总金额为人民币（大写）。** **¥：叁万陆仟玖佰元整**"
    },
    {
      "page": 1,
      "position": [
        544,
        2766,
        1977,
        2772,
        1978,
        2863,
        544,
        2857
      ],
      "type": "text",
      "content": "**单位开户行：建设银行银川东城支行**"
    },
    {
      "page": 1,
      "position": [
        539,
        2918,
        652,
        2918,
        652,
        3026,
        539,
        3026
      ],
      "type": "text",
      "content": "**账**"
    },
    {
      "page": 1,
      "position": [
        889,
        2927,
        2014,
        2927,
        2014,
        3015,
        889,
        3015
      ],
      "type": "text",
      "content": "**号：64050117010009999999**"
    },
    {
      "page": 1,
      "position": [
        580,
        3089,
        1171,
        3089,
        1171,
        3176,
        580,
        3176
      ],
      "type": "title",
      "level": 1,
      "content": "（二）供货时间"
    },
    {
      "page": 1,
      "position": [
        369,
        3248,
        3421,
        3248,
        3421,
        3661,
        369,
        3661
      ],
      "type": "text",
      "content": "卖方必须于合同生效之日起个工作日内将上述清单所列的货物送至买方指定的地点免费安装调试完毕且经买方验收合格，并承担运输过程中发生的一切手续和费用。"
    },
    {
      "page": 1,
      "position": [
        590,
        3727,
        1443,
        3735,
        1443,
        3826,
        590,
        3819
      ],
      "type": "title",
      "level": 1,
      "content": "（三）付款条件及方式"
    },
    {
      "page": 1,
      "position": [
        405,
        3884,
        3421,
        3884,
        3421,
        4285,
        405,
        4285
      ],
      "type": "text",
      "content": "实行财政集中支付的，当卖方忠实地履行了合同，买方向财政部门提交《中标通知书》《供货合同》《政府采购验收报告》，买方向卖方一次性支付合同款。"
    },
    {
      "page": 1,
      "position": [
        586,
        4363,
        1171,
        4363,
        1171,
        4450,
        586,
        4450
      ],
      "type": "title",
      "level": 1,
      "content": "（四）质量标准"
    },
    {
      "page": 1,
      "position": [
        369,
        4520,
        3436,
        4520,
        3436,
        4787,
        369,
        4787
      ],
      "type": "text",
      "content": "卖方所提供的货物必须是原厂原包装，质量必须符合国家标准和行业标准以及原厂出厂标准（以说明书为准），每个包装箱内的清单、使用说明书、质量证书、保修卡等所有资料应齐全。"
    },
    {
      "page": 2,
      "position": [
        580,
        534,
        1166,
        534,
        1166,
        624,
        580,
        624
      ],
      "type": "title",
      "level": 1,
      "content": "（五）技术文件"
    },
    {
      "page": 2,
      "position": [
        539,
        690,
        3082,
        690,
        3082,
        781,
        539,
        781
      ],
      "type": "text",
      "content": "1．卖方应在供货同时向买方提供所有有关本合同执行的技术文件。"
    },
    {
      "page": 2,
      "position": [
        374,
        842,
        3421,
        842,
        3421,
        1095,
        374,
        1095
      ],
      "type": "text",
      "content": "2．上述技术文件应包含保证卖方能够正确进行安装指导、操作、检查、维修、维护、测试、调试和运作需要的所有内容。"
    },
    {
      "page": 2,
      "position": [
        580,
        1157,
        997,
        1157,
        997,
        1244,
        580,
        1244
      ],
      "type": "title",
      "level": 1,
      "content": "（六）验收"
    },
    {
      "page": 2,
      "position": [
        539,
        1313,
        1685,
        1313,
        1685,
        1402,
        539,
        1402
      ],
      "type": "text",
      "content": "1．卖方负责产品的到货初验。"
    },
    {
      "page": 2,
      "position": [
        538,
        1465,
        2778,
        1472,
        2779,
        1561,
        539,
        1554
      ],
      "type": "text",
      "content": "卖方必须在到货的同时，向买方提供按本合同的设备数量。"
    },
    {
      "page": 2,
      "position": [
        534,
        1624,
        2039,
        1624,
        2039,
        1712,
        534,
        1712
      ],
      "type": "text",
      "content": "2．买方负责组织正式测试和验收工作。"
    },
    {
      "page": 2,
      "position": [
        369,
        1779,
        3431,
        1779,
        3431,
        2492,
        369,
        2492
      ],
      "type": "text",
      "content": "货物安装调试过程中，买方必须按本合同所约定的货物清单及要求对货物的品牌、外观、配件及安装调试后的使用性能等进行验收，卖方必须在验收现场提供必要的技术支持。买方应在产品安装调试并符合要求后的三个工作日内验收完毕。验收结果经买、卖双方确认后，买方必须对照本合同填好《政府采购验收报告》并签名、加盖单位的公章，由买方提交给卖方。"
    },
    {
      "page": 2,
      "position": [
        585,
        2553,
        1525,
        2559,
        1525,
        2647,
        585,
        2641
      ],
      "type": "title",
      "level": 1,
      "content": "（七）保修期及相关约定"
    },
    {
      "page": 2,
      "position": [
        370,
        2706,
        3431,
        2706,
        3431,
        3118,
        370,
        3118
      ],
      "type": "text",
      "content": "1．合同的质量保证期（简称“质保期”）为相应产品经买方及有权部门检测验收合格并交付买方使用之日起个月。质保期内卖方提供免费质量保修服务并按中华人民共和国有关行业规定进行质量“三包”。"
    },
    {
      "page": 2,
      "position": [
        374,
        3179,
        3426,
        3179,
        3426,
        3432,
        374,
        3432
      ],
      "type": "text",
      "content": "2．质保期内卖方应按国家有关规定对产品进行定期维护和维修。质保期满后，卖方有责任对产品进行定期维护和维修，有关维修合同另行签订。"
    },
    {
      "page": 2,
      "position": [
        375,
        3486,
        3426,
        3486,
        3426,
        3730,
        375,
        3730
      ],
      "type": "text",
      "content": "3．如果卖方延迟交货，则应向买方按延期交货支付货款总额得2‰的标准违约金。"
    },
    {
      "page": 2,
      "position": [
        539,
        3800,
        2999,
        3812,
        3000,
        3900,
        539,
        3888
      ],
      "type": "text",
      "content": "4如果买方延迟付款，则应向卖方按总额货款2‰的标准违约金。"
    },
    {
      "page": 2,
      "position": [
        544,
        3963,
        2871,
        3963,
        2871,
        4068,
        544,
        4068
      ],
      "type": "text",
      "content": "其它： 。"
    },
    {
      "page": 2,
      "position": [
        586,
        4123,
        1176,
        4123,
        1176,
        4209,
        586,
        4209
      ],
      "type": "title",
      "level": 1,
      "content": "（八）违约责任"
    },
    {
      "page": 2,
      "position": [
        374,
        4274,
        3431,
        4274,
        3431,
        4681,
        374,
        4681
      ],
      "type": "text",
      "content": "1．买方无正当理由不接收或不及时验收的，卖方有权按国家政府采购有关规定提请政府采购监督部门协调处理，若造成卖方损失的，按有关规定由买方赔偿卖方损失。"
    },
    {
      "page": 2,
      "position": [
        539,
        4741,
        3426,
        4757,
        3426,
        4848,
        539,
        4832
      ],
      "type": "text",
      "content": "2．本合同项下设备在质保期内由于卖方的原因产生的一切责任，均由卖方负责承担。"
    },
    {
      "page": 3,
      "position": [
        380,
        527,
        3421,
        527,
        3421,
        770,
        380,
        770
      ],
      "type": "text",
      "content": "3．质保期内，因买方原因或自然原因，产品及零配件出现问题的，卖方负责有偿更换。"
    },
    {
      "page": 3,
      "position": [
        539,
        835,
        2039,
        847,
        2039,
        937,
        539,
        924
      ],
      "type": "text",
      "content": "4．本合同有特别约定的按该约定执行。"
    },
    {
      "page": 3,
      "position": [
        539,
        994,
        3046,
        994,
        3046,
        1104,
        539,
        1104
      ],
      "type": "text",
      "content": "5．其它： 。"
    },
    {
      "page": 3,
      "position": [
        586,
        1153,
        1346,
        1153,
        1346,
        1241,
        586,
        1241
      ],
      "type": "title",
      "level": 1,
      "content": "（九）合同相关文件"
    },
    {
      "page": 3,
      "position": [
        544,
        1304,
        1813,
        1312,
        1813,
        1402,
        544,
        1394
      ],
      "type": "text",
      "content": "以下文件是合同不可分割的部分："
    },
    {
      "page": 3,
      "position": [
        528,
        1459,
        1972,
        1470,
        1972,
        1560,
        528,
        1548
      ],
      "type": "text",
      "content": "1．买方提供的公开招标文件及说明函；"
    },
    {
      "page": 3,
      "position": [
        524,
        1619,
        1099,
        1619,
        1099,
        1706,
        524,
        1706
      ],
      "type": "text",
      "content": "2．中标通知书；"
    },
    {
      "page": 3,
      "position": [
        370,
        1770,
        3421,
        1770,
        3421,
        2016,
        370,
        2016
      ],
      "type": "text",
      "content": "有关本次采购项目的采购文件以及相关的承诺函件等均视为本合同不可分割的一部分。"
    },
    {
      "page": 3,
      "position": [
        544,
        2080,
        1484,
        2089,
        1484,
        2178,
        544,
        2170
      ],
      "type": "title",
      "level": 1,
      "content": "（十）合同争议处理方式"
    },
    {
      "page": 3,
      "position": [
        374,
        2237,
        3421,
        2237,
        3421,
        2651,
        374,
        2651
      ],
      "type": "text",
      "content": "在本合同执行中所发生的一切争端，买卖双方应通过友好协商的办法加以解决。如从协商开始的30天内仍得不到解决，双方应将争端提交仲裁委员会申请仲裁；仲裁裁决为终局裁决，对双方均有约束力。"
    },
    {
      "page": 3,
      "position": [
        585,
        2702,
        2517,
        2716,
        2517,
        2807,
        585,
        2793
      ],
      "type": "title",
      "level": 2,
      "content": "（十一）本合同未尽事宜，由买、卖双方另行协商。"
    },
    {
      "page": 3,
      "position": [
        590,
        2860,
        3056,
        2875,
        3056,
        2965,
        590,
        2951
      ],
      "type": "text",
      "content": "（十二）本合同一式三份，买方、卖方、政府采购中心各执一份。"
    },
    {
      "page": 3,
      "position": [
        375,
        3298,
        1474,
        3298,
        1474,
        3400,
        375,
        3400
      ],
      "type": "text",
      "content": "买方：宁夏大学（研究生院）"
    },
    {
      "page": 3,
      "position": [
        1942,
        3308,
        3092,
        3308,
        3092,
        3416,
        1942,
        3416
      ],
      "type": "text",
      "content": "卖方：银川泽睿商贸有限公司"
    },
    {
      "page": 3,
      "position": [
        894,
        3431,
        2882,
        3431,
        2882,
        3544,
        894,
        3544
      ],
      "type": "text",
      "content": "（盖章） （盖章）"
    },
    {
      "type": "stamp",
      "page": 3,
      "position": [
        711,
        3152,
        1471,
        3151,
        1472,
        3899,
        712,
        3901
      ],
      "stamp": {
        "type": "公章",
        "shape": "圆章",
        "color": "红色",
        "content": "宁夏大学研究生院"
      },
      "text": "宁夏大学研究生院"
    },
    {
      "type": "stamp",
      "page": 3,
      "position": [
        2397,
        3261,
        3093,
        3261,
        3090,
        3961,
        2394,
        3961
      ],
      "stamp": {
        "type": "公章",
        "shape": "圆章",
        "color": "红色",
        "content": "银川泽睿商贸有限公司"
      },
      "text": "银川泽睿商贸有限公司"
    },
    {
      "page": 3,
      "position": [
        867,
        3638,
        1156,
        3651,
        1148,
        3807,
        860,
        3794
      ],
      "type": "text",
      "content": "王舒琪"
    },
    {
      "page": 3,
      "position": [
        2034,
        3683,
        2681,
        3683,
        2681,
        3811,
        2034,
        3811
      ],
      "type": "text",
      "content": "代表人： 方东安"
    },
    {
      "page": 3,
      "position": [
        370,
        3694,
        678,
        3694,
        678,
        3783,
        370,
        3783
      ],
      "type": "text",
      "content": "代表人："
    },
    {
      "page": 3,
      "position": [
        806,
        3827,
        3180,
        3827,
        3180,
        3932,
        806,
        3932
      ],
      "type": "text",
      "content": "（签字或盖章） （签字或盖章）"
    },
    {
      "page": 3,
      "position": [
        375,
        4089,
        632,
        4089,
        632,
        4173,
        375,
        4173
      ],
      "type": "text",
      "content": "日期："
    },
    {
      "page": 3,
      "position": [
        806,
        4089,
        1341,
        4089,
        1341,
        4192,
        806,
        4192
      ],
      "type": "text",
      "content": "年 月 日"
    },
    {
      "page": 3,
      "position": [
        2034,
        4101,
        2291,
        4101,
        2291,
        4188,
        2034,
        4188
      ],
      "type": "text",
      "content": "日期："
    },
    {
      "page": 3,
      "position": [
        2471,
        4099,
        3000,
        4099,
        3000,
        4207,
        2471,
        4207
      ],
      "type": "text",
      "content": "年 月 日"
    }
  ],
  "metadata": {
    "document_title": "宁夏大学政府采购合同",
    "buyer": "宁夏大学（研究生院） 电 话：09512061502",
    "seller": "银川泽睿商贸有限公司 电 话： 0951-5197939 根据《中华人民共和国政府采购法》《中华人民共和国合同法》和有关政府采购法规，依据公开招标文件及投标书，经买卖双方商定，同意按如下条款和条件签订",
    "contract_no": "2019NCZ001618W"
  }
}